scilaunch/__init__.py
scilaunch/configs.py
scilaunch/main.py
scilaunch/project.py
scilaunch/templates/cookiecutterrc/cookiecutter.json
scilaunch/templates/cookiecutterrc/{{cookiecutter._cache_dir}}/.cookiecutterrc
scilaunch-0.3.1.dist-info/licenses/LICENSE
scilaunch-0.3.1.dist-info/METADATA
scilaunch-0.3.1.dist-info/WHEEL
scilaunch-0.3.1.dist-info/entry_points.txt
scilaunch-0.3.1.dist-info/top_level.txt
scilaunch-0.3.1.dist-info/RECORD
