Metadata-Version: 2.4
Name: scilaunch
Version: 0.3.1
Summary: A tiny program for you, setting up the ground for grand discoveries. (2023)
Author-email: "Simon M. Hofmann" <simon.hofmann@pm.me>
Maintainer-email: "Simon M. Hofmann" <simon.hofmann@pm.me>
License: BSD License
Project-URL: GitHub, https://github.com/SHEscher/scilaunch
Project-URL: Cookiecutter-Template, https://github.com/SHEscher/research-project
Project-URL: Documentation, https://shescher.github.io/scilaunch/
Keywords: template,BIDS,reproducibilty,standardization
Platform: unix
Platform: linux
Platform: osx
Platform: cygwin
Platform: win32
Classifier: Development Status :: 3 - Alpha
Classifier: Intended Audience :: Science/Research
Classifier: Intended Audience :: Developers
Classifier: Natural Language :: English
Classifier: Programming Language :: Python :: 3
Classifier: Programming Language :: Python :: 3 :: Only
Classifier: Programming Language :: Python :: 3.9
Classifier: Programming Language :: Python :: 3.10
Classifier: Programming Language :: Python :: 3.11
Classifier: Programming Language :: Python :: 3.12
Classifier: Programming Language :: Python :: 3.13
Classifier: Programming Language :: Python :: 3.14
Requires-Python: >=3.9
License-File: LICENSE
Requires-Dist: cookiecutter<3.0,>=2.6.0
Requires-Dist: GitPython<4.0,>=3.1
Requires-Dist: python-box<8.0,>=7.0
Requires-Dist: pyyaml<7.0,>=5.3
Provides-Extra: develop
Requires-Dist: bumpver==2025.1131; extra == "develop"
Requires-Dist: ruff<2.0.0,>=0.14.10; extra == "develop"
Requires-Dist: tox<4.31.0,>=4.30.2; extra == "develop"
Requires-Dist: pytest<10.0.0,>=9.0.2; extra == "develop"
Requires-Dist: pytest-cov; extra == "develop"
Requires-Dist: toml<0.11.0,>=0.10.2; extra == "develop"
Requires-Dist: ty<2.0.0,>=0.0.4; extra == "develop"
Provides-Extra: docs
Requires-Dist: blacken-docs>=1.13; extra == "docs"
Requires-Dist: docutils>=0.20.1; extra == "docs"
Requires-Dist: markdown-callouts>=0.2; extra == "docs"
Requires-Dist: markdown-exec[ansi]>=0.5; extra == "docs"
Requires-Dist: mkdocs>=1.5; extra == "docs"
Requires-Dist: mkdocs-autorefs>=0.5.0; extra == "docs"
Requires-Dist: mkdocs-coverage>=0.2; extra == "docs"
Requires-Dist: mkdocs-gen-files>=0.3; extra == "docs"
Requires-Dist: mkdocs-literate-nav>=0.4; extra == "docs"
Requires-Dist: mkdocs-material>=7.3; extra == "docs"
Requires-Dist: mkdocs-material-extensions; extra == "docs"
Requires-Dist: mkdocs-minify-plugin>=0.6.4; extra == "docs"
Requires-Dist: mkdocs-redirects>=1.2.0; extra == "docs"
Requires-Dist: mkdocstrings[python]; extra == "docs"
Requires-Dist: pypandoc>=1.12; extra == "docs"
Dynamic: license-file
